synotools/__init__.py
synotools/constants.py
synotools/settings.py
synotools/commands/__init__.py
synotools/commands/constants.py
synotools/commands/download.py
synotools/commands/install.py
synotools/commands/vpn_connect.py
synotools/common/__init__.py
synotools/common/exceptions.py
synotools/common/logging.py
synotools/common/utils.py
synotools/models/__init__.py
synotools/models/base.py
synotools/models/config/__init__.py
synotools/models/config/base.py
synotools/models/config/deluge.py
synotools/models/config/syno.py
synotools/models/config/vpn.py
synotools/scripts/__init__.py
synotools-0.5.1.dist-info/LICENSE
synotools-0.5.1.dist-info/METADATA
synotools-0.5.1.dist-info/WHEEL
synotools-0.5.1.dist-info/top_level.txt
synotools-0.5.1.dist-info/RECORD
