Metadata-Version: 2.1
Name: synotools
Version: 0.5.1
Summary: A Python API wrapper and toolset to interact with Synology NAS devices.
Home-page: https://github.com/DazEdword/synology-toolset
Author: Ed Garabito
Author-email: eduardo@gottabegarabi.com
License: UNKNOWN
Platform: UNKNOWN
Classifier: Programming Language :: Python :: 3
Classifier: License :: OSI Approved :: MIT License
Classifier: Operating System :: OS Independent
Requires-Dist: fabric
Requires-Dist: python-dotenv
Requires-Dist: python-synology
